FinCrawl/CrawlData.py
FinCrawl/__init__.py
FinCrawl/engines/__init__.py
FinCrawl/engines/comments.py
FinCrawl/engines/industry.py
FinCrawl/engines/news.py
FinCrawl/engines/report.py
FinCrawl/engines/stocklist.py
FinCrawl/engines/stockprice.py
FinCrawl/tools/__init__.py
FinCrawl/tools/timetools.py
FinCrawl/urls/__init__.py
FinCrawl/urls/urls.py
FinCrawl-0.0.1.dist-info/LICENSE
FinCrawl-0.0.1.dist-info/METADATA
FinCrawl-0.0.1.dist-info/WHEEL
FinCrawl-0.0.1.dist-info/top_level.txt
FinCrawl-0.0.1.dist-info/RECORD
