Metadata-Version: 2.1
Name: FinCrawl
Version: 0.0.1
Summary: A package for crawling financial textual data
Home-page: UNKNOWN
Author: Kyle Xie
Author-email: xiecong@ruc.edu.cn
License: UNKNOWN
Platform: UNKNOWN
Classifier: Programming Language :: Python :: 3
Classifier: License :: OSI Approved :: MIT License
Classifier: Operating System :: OS Independent
Requires-Python: >=3.6
